pyturbo/__init__.py
pyturbo/cli.py
pyturbo/config.py
pyturbo/version.py
pyturbo/core/__init__.py
pyturbo/core/frame.py
pyturbo/core/operations.py
pyturbo_analytics-0.1.2.dist-info/LICENSE
pyturbo_analytics-0.1.2.dist-info/METADATA
pyturbo_analytics-0.1.2.dist-info/WHEEL
pyturbo_analytics-0.1.2.dist-info/entry_points.txt
pyturbo_analytics-0.1.2.dist-info/top_level.txt
pyturbo_analytics-0.1.2.dist-info/RECORD
